agentic_proteins/__init__.py
agentic_proteins/py.typed
agentic_proteins/agents/__init__.py
agentic_proteins/agents/schemas.py
agentic_proteins/agents/analysis/__init__.py
agentic_proteins/agents/analysis/failure_analysis.py
agentic_proteins/agents/analysis/sequence_analysis.py
agentic_proteins/agents/analysis/structure.py
agentic_proteins/agents/base/__init__.py
agentic_proteins/agents/base/base.py
agentic_proteins/agents/execution/__init__.py
agentic_proteins/agents/execution/coordinator.py
agentic_proteins/agents/planning/__init__.py
agentic_proteins/agents/planning/compiler.py
agentic_proteins/agents/planning/generation.py
agentic_proteins/agents/planning/planner.py
agentic_proteins/agents/planning/schemas.py
agentic_proteins/agents/planning/validation.py
agentic_proteins/agents/reporting/__init__.py
agentic_proteins/agents/reporting/reporting.py
agentic_proteins/agents/verification/__init__.py
agentic_proteins/agents/verification/critic.py
agentic_proteins/agents/verification/input_validation.py
agentic_proteins/agents/verification/quality_control.py
agentic_proteins/api/__init__.py
agentic_proteins/api/app.py
agentic_proteins/api/deps.py
agentic_proteins/api/errors.py
agentic_proteins/api/middleware.py
agentic_proteins/api/v1/__init__.py
agentic_proteins/api/v1/router.py
agentic_proteins/api/v1/schema.py
agentic_proteins/api/v1/endpoints/compare.py
agentic_proteins/api/v1/endpoints/inspect.py
agentic_proteins/api/v1/endpoints/resume.py
agentic_proteins/api/v1/endpoints/run.py
agentic_proteins/biology/__init__.py
agentic_proteins/biology/pathway.py
agentic_proteins/biology/protein_agent.py
agentic_proteins/biology/regulator.py
agentic_proteins/biology/signals.py
agentic_proteins/biology/validation.py
agentic_proteins/core/__init__.py
agentic_proteins/core/api_lock.py
agentic_proteins/core/contracts.py
agentic_proteins/core/costs.py
agentic_proteins/core/decisions.py
agentic_proteins/core/determinism.py
agentic_proteins/core/execution.py
agentic_proteins-0.2.3.dist-info/METADATA
agentic_proteins-0.2.3.dist-info/WHEEL
agentic_proteins-0.2.3.dist-info/entry_points.txt
agentic_proteins-0.2.3.dist-info/licenses/LICENSE
agentic_proteins-0.2.3.dist-info/RECORD
